supertable/__init__.py
supertable/data_classes.py
supertable/data_estimator.py
supertable/data_reader.py
supertable/data_writer.py
supertable/execute_duckdb.py
supertable/execute_spark.py
supertable/executor.py
supertable/history_cleaner.py
supertable/meta_reader.py
supertable/monitoring_reader.py
supertable/monitoring_writer.py
supertable/plan_extender.py
supertable/plan_stats.py
supertable/processing.py
supertable/query_plan_manager.py
supertable/redis_catalog.py
supertable/simple_table.py
supertable/staging_area.py
supertable/super_pipe.py
supertable/super_table.py
supertable/api/__init__.py
supertable/api/api.py
supertable/api/application.py
supertable/api/auth.py
supertable/api/test_api.py
supertable/config/__init__.py
supertable/config/cli.py
supertable/config/defaults.py
supertable/config/homedir.py
supertable/locking/__init__.py
supertable/locking/file_lock.py
supertable/locking/locking.py
supertable/locking/locking_backend.py
supertable/locking/redis_lock.py
supertable/locking/simulations/__init__.py
supertable/locking/simulations/concurrency_lock_simulation.py
supertable/locking/simulations/escalate_lock.py
supertable/locking/simulations/measure_lock_speed.py
supertable/locking/simulations/measure_lock_time.py
supertable/mcp/__init__.py
supertable/mcp/mcp_client.py
supertable/mcp/mcp_server.py
supertable/mcp/test_mcp_server_transport.py
supertable/mcp/test_web_client.py
supertable/mcp/web_app.py
supertable/mcp/web_client.py
supertable/mcp/web_server.py
supertable/mirroring/__init__.py
supertable/mirroring/mirror_delta.py
supertable/mirroring/mirror_formats.py
supertable/mirroring/mirror_iceberg.py
supertable/mirroring/mirror_parquet.py
supertable/rbac/__init__.py
supertable/rbac/access_control.py
supertable/rbac/filter_builder.py
supertable/rbac/permissions.py
supertable/rbac/redis_repo.py
supertable/rbac/role_manager.py
supertable/rbac/row_column_security.py
supertable/rbac/user_manager.py
supertable/reflection/__init__.py
supertable-1.5.6.dist-info/licenses/LICENSE
supertable-1.5.6.dist-info/METADATA
supertable-1.5.6.dist-info/WHEEL
supertable-1.5.6.dist-info/entry_points.txt
supertable-1.5.6.dist-info/top_level.txt
supertable-1.5.6.dist-info/RECORD
