Metadata-Version: 2.4
Name: supertable
Version: 1.5.6
Summary: SuperTable revolutionizes data management by integrating multiple basic tables into a single, cohesive framework.
Author: Levente Kupas
Author-email: Levente Kupas <lkupas@kladnasoft.com>
License: Super Table Public Use License (STPUL) v1.0
Project-URL: Homepage, https://github.com/kladnasoft/supertable
Classifier: Programming Language :: Python :: 3
Classifier: Programming Language :: Python :: 3 :: Only
Classifier: License :: Other/Proprietary License
Classifier: Operating System :: OS Independent
Requires-Python: >=3.10
License-File: LICENSE
Requires-Dist: numpy<2.0,>=1.26
Requires-Dist: pandas<2.3,>=2.1
Requires-Dist: pyarrow<19,>=16
Requires-Dist: pytz>=2023.3
Requires-Dist: tzdata>=2023.3
Requires-Dist: duckdb<2.0,>=1.1
Requires-Dist: polars<2.0,>=1.6
Requires-Dist: sqlglot<27,>=26
Requires-Dist: colorlog<7.0,>=6.9
Requires-Dist: python-dotenv<2.0,>=1.0
Requires-Dist: setuptools>=68
Requires-Dist: redis<5.2,>=5.0
Requires-Dist: minio<8.0,>=7.2
Requires-Dist: boto3<2.0,>=1.34
Requires-Dist: fastapi<0.117,>=0.111
Requires-Dist: uvicorn[standard]<0.34,>=0.30
Requires-Dist: jinja2<3.2,>=3.1
Requires-Dist: aiofiles<24.0,>=23.2
Requires-Dist: orjson<4.0,>=3.9
Requires-Dist: mcp>=1.1.0
Provides-Extra: s3
Requires-Dist: boto3>=1.40.30; extra == "s3"
Requires-Dist: redis>=6.4.0; extra == "s3"
Provides-Extra: minio
Requires-Dist: minio>=7.2.15; extra == "minio"
Requires-Dist: redis>=6.4.0; extra == "minio"
Provides-Extra: azure
Requires-Dist: azure-storage-blob>=12.26.0; extra == "azure"
Requires-Dist: redis>=6.4.0; extra == "azure"
Provides-Extra: gcp
Requires-Dist: google-cloud-storage>=3.1.0; extra == "gcp"
Requires-Dist: redis>=6.4.0; extra == "gcp"
Provides-Extra: all-cloud
Requires-Dist: supertable[azure,gcp,minio,s3]; extra == "all-cloud"
Dynamic: author
Dynamic: license-file
Dynamic: requires-python
